inuits_otel_tracer/tracer.py
inuits_otel_tracer-0.0.9.dist-info/METADATA
inuits_otel_tracer-0.0.9.dist-info/WHEEL
inuits_otel_tracer-0.0.9.dist-info/top_level.txt
inuits_otel_tracer-0.0.9.dist-info/RECORD
