Metadata-Version: 2.1
Name: inuits-otel-tracer
Version: 0.0.9
Summary: Otel tracer help for tracing in python applications.
Author: Yasinthan Subakaran
Author-email: yasinthan@inuits.eu
License: GPLv2
Classifier: License :: OSI Approved :: GNU General Public License v2 (GPLv2)
Classifier: Intended Audience :: Developers
Classifier: Programming Language :: Python :: 3
Provides: inuits_otel_tracer
Requires-Dist: backoff (==1.10.0)
Requires-Dist: Deprecated (==1.2.13)
Requires-Dist: googleapis-common-protos (==1.56.3)
Requires-Dist: grpcio (==1.46.3)
Requires-Dist: opentelemetry-api (==1.9.1)
Requires-Dist: opentelemetry-exporter-otlp (==1.9.1)
Requires-Dist: opentelemetry-exporter-otlp-proto-grpc (==1.9.1)
Requires-Dist: opentelemetry-exporter-otlp-proto-http (==1.9.1)
Requires-Dist: opentelemetry-instrumentation (==0.28b1)
Requires-Dist: opentelemetry-instrumentation-flask (==0.28b1)
Requires-Dist: opentelemetry-instrumentation-requests (==0.28b1)
Requires-Dist: opentelemetry-instrumentation-wsgi (==0.28b1)
Requires-Dist: opentelemetry-proto (==1.9.1)
Requires-Dist: opentelemetry-sdk (==1.9.1)
Requires-Dist: opentelemetry-semantic-conventions (==0.28b1)
Requires-Dist: opentelemetry-util-http (==0.28b1)
Requires-Dist: protobuf (==3.20.1)
Requires-Dist: typing-extensions (==4.2.0)
Requires-Dist: wrapt (==1.14.1)
